ornl_presto/__init__.py
ornl_presto/core.py
ornl_presto-0.1.27.dist-info/LICENSE
ornl_presto-0.1.27.dist-info/METADATA
ornl_presto-0.1.27.dist-info/WHEEL
ornl_presto-0.1.27.dist-info/top_level.txt
ornl_presto-0.1.27.dist-info/RECORD
