Metadata-Version: 2.1
Name: ornl_presto
Version: 0.1.27
Summary: A Python package for privacy preservation algorithm recomendation
Home-page: https://github.com/OKotevska/PRESTO/
Author: Olivera Kotevska
Author-email: Olivera Kotevska <kotevskao@ornl.gov>
License: MIT License
Project-URL: Homepage, https://github.com/ORNL/PRESTO/
Requires-Python: >=3.7
License-File: LICENSE
Requires-Dist: torch
Requires-Dist: numpy
Requires-Dist: seaborn
Requires-Dist: pandas
Requires-Dist: scipy
Requires-Dist: matplotlib
Requires-Dist: bayesian-optimization
Requires-Dist: gpytorch
Requires-Dist: scikit-learn
Requires-Dist: opacus
